djangoldp_sales/__init__.py
djangoldp_sales/admin.py
djangoldp_sales/apps.py
djangoldp_sales/djangoldp_settings.py
djangoldp_sales/djangoldp_urls.py
djangoldp_sales/models.py
djangoldp_sales/tests.py
djangoldp_sales/views.py
djangoldp_sales/migrations/0001_initial.py
djangoldp_sales/migrations/0002_auto_20220211_1514.py
djangoldp_sales/migrations/0003_auto_20220214_1816.py
djangoldp_sales/migrations/0004_auto_20220215_1821.py
djangoldp_sales/migrations/0005_auto_20220215_1823.py
djangoldp_sales/migrations/0006_productstock.py
djangoldp_sales/migrations/0007_auto_20220303_2033.py
djangoldp_sales/migrations/0008_auto_20220303_2057.py
djangoldp_sales/migrations/0009_order.py
djangoldp_sales/migrations/0010_remove_order_product.py
djangoldp_sales/migrations/0011_order_client.py
djangoldp_sales/migrations/0012_auto_20220308_1815.py
djangoldp_sales/migrations/0013_order_orderquantity.py
djangoldp_sales/migrations/0014_auto_20220308_1824.py
djangoldp_sales/migrations/0015_auto_20220308_1826.py
djangoldp_sales/migrations/0016_order_orderstatus.py
djangoldp_sales/migrations/0017_order_transactiondate.py
djangoldp_sales/migrations/0018_auto_20220311_1134.py
djangoldp_sales/migrations/0019_product_author.py
djangoldp_sales/migrations/0020_order_sale.py
djangoldp_sales/migrations/0021_order_totalprice.py
djangoldp_sales/migrations/__init__.py
djangoldp_sales/templates/client_order.txt
djangoldp_sales/templates/owner_order.txt
djangoldp_sales-0.0.14.dist-info/METADATA
djangoldp_sales-0.0.14.dist-info/WHEEL
djangoldp_sales-0.0.14.dist-info/top_level.txt
djangoldp_sales-0.0.14.dist-info/RECORD
